shared_jwt_service/__init__.py
shared_jwt_service/jwt.py
shared_jwt_service-0.1.0.dist-info/WHEEL
shared_jwt_service-0.1.0.dist-info/entry_points.txt
shared_jwt_service-0.1.0.dist-info/METADATA
shared_jwt_service-0.1.0.dist-info/RECORD
