Metadata-Version: 2.3
Name: shared-jwt-service
Version: 0.1.0
Summary: A Simple library to get certain JWT for later uses in different projects mainly to get the user_id from the header
Author: Ndaedzo Mudau
Author-email: Ndaedzo Mudau <ndaedzomu101@gmail.com>
Requires-Dist: fastapi
Requires-Dist: pyjwt
Requires-Python: >=3.10
